cerulean/__init__.py
cerulean/copy_files.py
cerulean/credential.py
cerulean/direct_gnu_scheduler.py
cerulean/factory.py
cerulean/file_system.py
cerulean/file_system_impl.py
cerulean/job_description.py
cerulean/job_status.py
cerulean/local_file_system.py
cerulean/local_terminal.py
cerulean/path.py
cerulean/py.typed
cerulean/scheduler.py
cerulean/sftp_file_system.py
cerulean/slurm_scheduler.py
cerulean/ssh_terminal.py
cerulean/terminal.py
cerulean/torque_scheduler.py
cerulean/webdav_file_system.py
cerulean/test/__init__.py
cerulean/test/conftest.py
cerulean/test/test_copy_files.py
cerulean/test/test_credential.py
cerulean/test/test_factory.py
cerulean/test/test_file_systems.py
cerulean/test/test_path.py
cerulean/test/test_scheduler.py
cerulean/test/test_slurm_scheduler.py
cerulean/test/test_ssh_terminal.py
cerulean/test/test_terminal.py
cerulean/test/test_torque_scheduler.py
cerulean/test/test_webdav_file_system.py
cerulean-1.0.0.dist-info/LICENSE
cerulean-1.0.0.dist-info/METADATA
cerulean-1.0.0.dist-info/NOTICE
cerulean-1.0.0.dist-info/WHEEL
cerulean-1.0.0.dist-info/top_level.txt
cerulean-1.0.0.dist-info/RECORD
