Metadata-Version: 2.2
Name: cerulean
Version: 1.0.0
Summary: A Python library for talking to HPC clusters and supercomputers
Author: Lourens Veen
Classifier: Development Status :: 5 - Production/Stable
Classifier: Intended Audience :: Developers
Classifier: License :: OSI Approved :: Apache Software License
Classifier: Natural Language :: English
Classifier: Programming Language :: Python :: 3
Classifier: Programming Language :: Python :: 3.8
Classifier: Programming Language :: Python :: 3.9
Classifier: Programming Language :: Python :: 3.10
Classifier: Programming Language :: Python :: 3.11
Classifier: Programming Language :: Python :: 3.12
Classifier: Programming Language :: Python :: 3.13
Requires-Python: >=3.8
License-File: LICENSE
License-File: NOTICE
Requires-Dist: defusedxml
Requires-Dist: paramiko
Requires-Dist: requests
Requires-Dist: types-requests
